jiraworklog/__init__.py
jiraworklog/application.py
jiraworklog/auth_jira.py
jiraworklog/cmdline_args.py
jiraworklog/configuration.py
jiraworklog/confirm_updates.py
jiraworklog/delete_worklog.py
jiraworklog/diff_worklogs.py
jiraworklog/exceptions.py
jiraworklog/init_config.py
jiraworklog/read_checkedin_worklogs.py
jiraworklog/read_local_common.py
jiraworklog/read_local_delimited.py
jiraworklog/read_local_excel.py
jiraworklog/read_remote_worklogs.py
jiraworklog/reconcile_diffs.py
jiraworklog/sync_worklogs.py
jiraworklog/update_instructions.py
jiraworklog/utils.py
jiraworklog/worklogs.py
jiraworklog-0.1.3.dist-info/entry_points.txt
jiraworklog-0.1.3.dist-info/WHEEL
jiraworklog-0.1.3.dist-info/METADATA
jiraworklog-0.1.3.dist-info/RECORD
