Metadata-Version: 2.1
Name: jiraworklog
Version: 0.1.3
Summary: Command-line application to synchronize local worklog records with a Jira server
Home-page: https://github.com/dapritchard/jiraworklog
Author: David Pritchard
Author-email: david.al.pritchard@gmail.com
Requires-Python: >=3.9,<4.0
Classifier: Programming Language :: Python :: 3
Classifier: Programming Language :: Python :: 3.9
Classifier: Programming Language :: Python :: 3.10
Requires-Dist: Cerberus (>=1.3.4)
Requires-Dist: PyYAML (>=6.0)
Requires-Dist: jira (>=3.3.0)
Requires-Dist: openpyxl (>=3.0.10)
Requires-Dist: prettyprinter (>=0.18.0)
Requires-Dist: pytz (>=2022.1)
Project-URL: Repository, https://github.com/dapritchard/jiraworklog
